simplesbml/__init__.py
simplesbml-1.2.2.dist-info/DESCRIPTION.rst
simplesbml-1.2.2.dist-info/METADATA
simplesbml-1.2.2.dist-info/RECORD
simplesbml-1.2.2.dist-info/WHEEL
simplesbml-1.2.2.dist-info/metadata.json
simplesbml-1.2.2.dist-info/top_level.txt
