Metadata-Version: 2.0
Name: simplesbml
Version: 1.2.2
Summary: A simplified interface for constructing SBML docs.
Home-page: http://simplesbml.readthedocs.io/en/latest/
Author: Caroline Cannistra, Kyle Medley
Author-email: tellurium-discuss@googlegroups.com
License: UNKNOWN
Platform: UNKNOWN
Requires-Dist: tesbml (>=5.15.0)
